algoapi/__init__.py
algoapi/base.py
algoapi/exceptions.py
algoapi/filter.py
algoapi/signal.py
algoapi/tradingview.py
examples/filter/create_update_delete_filter.py
examples/filter/get_all_filters.py
examples/filter/get_filter_by_id.py
examples/filter/get_filter_range.py
examples/filter/run_filter.py
examples/filter/run_filter_by_id.py
examples/signal/get_formula_signal.py
examples/signal/get_signal_histories.py
examples/signal/get_signals.py
examples/signal/get_signals_by_status.py
examples/signal/register_unsubcribe_signal.py
examples/tradingview/get_and_search_symbols.py
examples/tradingview/get_history.py
examples/tradingview/get_time_and_config.py
examples/tradingview/user_charts.py
pyalgoapi-1.0.1.dist-info/METADATA
pyalgoapi-1.0.1.dist-info/WHEEL
pyalgoapi-1.0.1.dist-info/RECORD
