Metadata-Version: 2.1
Name: pyalgoapi
Version: 1.0.1
Summary: Python Wrapper for BSC Algo API
Author: Trung Dang
Author-email: trungd@bsc.com.vn
Requires-Python: >=3.11,<4.0
Classifier: Programming Language :: Python :: 3
Classifier: Programming Language :: Python :: 3.11
Requires-Dist: requests (>=2.31.0,<3.0.0)
